{
    "projectId":"TSDL-Smart-Monkey-with-cypress",
    "baseUrl":"http://host.docker.internal:2368",
    "env":{
        "appName":"App prueba",
        "events":200,
        "delay":1000,
        "seed":1111,
        "pctClicks":12,
        "pctScroll":12,
        "pctSelectors":12,
        "pctKeys":12,
        "pctSpKeys":12,
        "pctPgNav":12,
        "pctBwChaos":12,
        "pctActions":16
    },
    "integrationFolder": "./cypress/integration/monkey",
    "pluginsFile": "./cypress/plugins/index.js",
    "pageLoadTimeout":4000,
    "defaultCommandTimeout":4000,
    "testFiles": "smart-monkey.js",
    "videosFolder":"./results"
}
